lrjson/__init__.py
lrjson/__main__.py
lrjson/convert_lr_to_json.py
lrjson-0.0.1.dist-info/METADATA
lrjson-0.0.1.dist-info/WHEEL
lrjson-0.0.1.dist-info/entry_points.txt
lrjson-0.0.1.dist-info/top_level.txt
lrjson-0.0.1.dist-info/RECORD
