Metadata-Version: 2.1
Name: lrjson
Version: 0.0.1
Summary: Convert Lightroom Template file .ltemplate into manipulable JSON file
Home-page: https://github.com/remiflavien1/lrjson
Author: shadawck
Author-email: hug211mire@gmail.com
License: MIT
Platform: UNKNOWN
Classifier: License :: OSI Approved :: MIT License
Classifier: Programming Language :: Python :: 3
Classifier: Programming Language :: Python :: 3.7
Requires-Dist: docopt
